<?xml version="1.0" encoding="utf-8"?>
<savedqueries>
  <savedquery>
    <IsCustomizable>1</IsCustomizable>
    <CanBeDeleted>0</CanBeDeleted>
    <isquickfindquery>0</isquickfindquery>
    <isprivate>0</isprivate>
    <isdefault>0</isdefault>
    <savedqueryid>{faf0e4f9-8a17-439e-9c1f-8c5407abf343}</savedqueryid>
    <layoutxml>
      <grid name="resultset" jump="smp_regionname" select="1" icon="1" preview="1">
        <row name="result" id="smp_regionid">
          <cell name="smp_regionname" width="300" />
          <cell name="createdon" width="125" />
        </row>
      </grid>
    </layoutxml>
    <querytype>0</querytype>
    <fetchxml>
      <fetch version="1.0" mapping="logical">
        <entity name="smp_region">
          <attribute name="smp_regionid" />
          <attribute name="smp_regionname" />
          <attribute name="createdon" />
          <order attribute="smp_regionname" descending="false" />
          <filter type="and">
            <condition attribute="statecode" operator="eq" value="1" />
          </filter>
        </entity>
      </fetch>
    </fetchxml>
    <IntroducedVersion>1.0</IntroducedVersion>
    <LocalizedNames>
      <LocalizedName description="Inactive Regions" languagecode="1033" />
    </LocalizedNames>
  </savedquery>
</savedqueries>